credstuffer/__init__.py
credstuffer/account.py
credstuffer/algorithm.py
credstuffer/app.py
credstuffer/database_stuffer.py
credstuffer/dbhandler.py
credstuffer/directory_stuffer.py
credstuffer/email_account.py
credstuffer/exceptions.py
credstuffer/file_stuffer.py
credstuffer/proxy.py
credstuffer/stuffer.py
credstuffer/tor.py
credstuffer/user_account.py
credstuffer/accounts/__init__.py
credstuffer/accounts/comunio.py
credstuffer/accounts/facebook.py
credstuffer/accounts/instagram.py
credstuffer/accounts/twitter.py
credstuffer/db/__init__.py
credstuffer/db/connector.py
credstuffer/db/context.py
credstuffer/db/creator.py
credstuffer/db/fetcher.py
credstuffer/db/inserter.py
credstuffer/db/sqlite.py
credstuffer/notification/__init__.py
credstuffer/notification/credstuffer_telegram.py
credstuffer/notification/mail.py
credstuffer/test/__init__.py
credstuffer/test/test_proxy.py
credstuffer/test/accounts/__init__.py
credstuffer/test/accounts/test_comunio.py
credstuffer/test/accounts/test_instagram.py
credstuffer/test/db/__init__.py
credstuffer/test/db/test_connector.py
credstuffer/test/db/test_creator.py
credstuffer/test/db/test_fetcher.py
credstuffer/test/db/test_inserter.py
credstuffer/test/notification/__init__.py
credstuffer/test/notification/test_mail.py
credstuffer/test/notification/test_telegram.py
credstuffer/utils/__init__.py
credstuffer/utils/logger.py
credstuffer-1.0.13.dist-info/LICENSE
credstuffer-1.0.13.dist-info/METADATA
credstuffer-1.0.13.dist-info/WHEEL
credstuffer-1.0.13.dist-info/entry_points.txt
credstuffer-1.0.13.dist-info/top_level.txt
credstuffer-1.0.13.dist-info/RECORD
