Metadata-Version: 2.1
Name: credstuffer
Version: 1.0.13
Summary: credentials stuffer
Home-page: https://github.com/bierschi/credstuffer
Author: Christian Bierschneider
Author-email: christian.bierschneider@web.de
License: MIT
Keywords: credstuffer,credentials,stuffing,hacking,bruteforce
Platform: UNKNOWN
Classifier: Development Status :: 4 - Beta
Classifier: Intended Audience :: Developers
Classifier: Intended Audience :: End Users/Desktop
Classifier: License :: OSI Approved :: MIT License
Classifier: Operating System :: OS Independent
Classifier: Programming Language :: Python
Classifier: Programming Language :: Python :: 3
Classifier: Programming Language :: Python :: 3.3
Classifier: Programming Language :: Python :: 3.4
Classifier: Programming Language :: Python :: 3.5
Classifier: Programming Language :: Python :: 3.6
Classifier: Programming Language :: Python :: Implementation :: PyPy
Requires-Python: >=3
Requires-Dist: requests (>=2.22.0)
Requires-Dist: PySocks (>=1.7.1)
Requires-Dist: psycopg2 (>=2.8.3)
Requires-Dist: python-telegram-bot (>=12.1.1)
Requires-Dist: stem (>=1.7.1)
